main.py
my_first_mcp_server-0.1.0.dist-info/METADATA
my_first_mcp_server-0.1.0.dist-info/WHEEL
my_first_mcp_server-0.1.0.dist-info/top_level.txt
my_first_mcp_server-0.1.0.dist-info/RECORD
