Metadata-Version: 2.4
Name: my-first-mcp-server
Version: 0.1.0
Summary: Add your description here
Requires-Python: >=3.12
Requires-Dist: mcp[cli]>=1.9.4
